axi_interface/axi_self_test.v
`define CONFIG_WRITE_OUTRANGE 8'b1000_1000

module axi_self_test #(
    parameter integer C_S_AXI_ID_WIDTH    	= 1,
    parameter integer C_S_AXI_DATA_WIDTH    = 32,
    parameter integer C_S_AXI_ADDR_WIDTH    = 8, // 0x00~0xFF : maximum 256 bytes
    parameter integer C_S_AXI_AWUSER_WIDTH  = 0,
    parameter integer C_S_AXI_ARUSER_WIDTH  = 0,
    parameter integer C_S_AXI_WUSER_WIDTH   = 0,
    parameter integer C_S_AXI_RUSER_WIDTH   = 0,
    parameter integer C_S_AXI_BUSER_WIDTH   = 0,
    parameter integer CONFIG_AREA          	= 16, // 0x80~0x8F
    parameter integer WRITE_AREA          	= 64, // 0x00~0x3F
    parameter integer READ_AREA          	= 64  // 0x40~0xF
)(
    // Clock and Reset
    input  wire                              S_AXI_ACLK,
    input  wire                              S_AXI_ARESETN,

    // Write Address Channel
    input  wire [C_S_AXI_ADDR_WIDTH-1:0]     S_AXI_AWADDR,
    input  wire                              S_AXI_AWVALID,
    output reg                               S_AXI_AWREADY,

    // Write Data Channel
    input  wire [C_S_AXI_DATA_WIDTH-1:0]     S_AXI_WDATA,
    input  wire                              S_AXI_WVALID,
    output reg                               S_AXI_WREADY,

    // Read Address Channel
    input  wire [C_S_AXI_ADDR_WIDTH-1:0]     S_AXI_ARADDR,
    input  wire                              S_AXI_ARVALID,
    output reg                               S_AXI_ARREADY,

    // Read Data Channel
    output reg [C_S_AXI_DATA_WIDTH-1:0]      S_AXI_RDATA,
    output reg                               S_AXI_RVALID,
    input  wire                              S_AXI_RREADY
);

parameter integer REG_RW_DEPTH = WRITE_AREA + READ_AREA;
reg [C_S_AXI_DATA_WIDTH-1:0] axi_reg_rw     [0:REG_RW_DEPTH-1];
reg [C_S_AXI_DATA_WIDTH-1:0] axi_reg_cfg    [0:CONFIG_AREA-1];

wire is_config_area;
assign is_config_area = axi_awaddr[C_S_AXI_ADDR_WIDTH-1];

// Register for internal address storage
reg [C_S_AXI_ADDR_WIDTH-1:0] axi_araddr;
reg [C_S_AXI_ADDR_WIDTH-1:0] axi_awaddr;

// ----------------------
// Write Address Channel
// ----------------------
always @(posedge S_AXI_ACLK) begin
    if (!S_AXI_ARESETN) begin
        S_AXI_AWREADY <= 1'b0;
        axi_awaddr <= 0;
    end
    else begin
        if (~S_AXI_AWREADY && S_AXI_AWVALID) begin
            // 接受写地址
            S_AXI_AWREADY <= 1'b1;
            axi_awaddr <= S_AXI_AWADDR;
        end
        else begin
            S_AXI_AWREADY <= 1'b0;
        end
    end
end

// ----------------------
// Write Data Channel
// ----------------------
always @(posedge S_AXI_ACLK) begin
    if (!S_AXI_ARESETN) begin
        S_AXI_WREADY <= 1'b0;
    end
    else begin
        if (~S_AXI_WREADY && S_AXI_WVALID) begin
            // 接受写数据
            S_AXI_WREADY <= 1'b1;
        end
        else begin
            S_AXI_WREADY <= 1'b0;
        end
    end
end

// 写数据到寄存器
always @(posedge S_AXI_ACLK) begin
    if (!S_AXI_ARESETN) begin
        integer i;
        for (i = 0; i < REG_RW_DEPTH; i = i + 1) begin
            axi_reg_rw[i] <= 0;
        end
    end
    else begin
        if (S_AXI_WREADY && S_AXI_WVALID && S_AXI_AWREADY && S_AXI_AWVALID && ~is_config_area) begin
            // 当地址和数据都有效时，执行写操作
            axi_reg_rw[axi_awaddr] <= S_AXI_WDATA;
            // If the address is out of the write area, write a special value to a specific register in the config area
            if (axi_awaddr >= WRITE_AREA && ~is_config_area) begin
                axi_reg_cfg[`CONFIG_WRITE_OUTRANGE] <= axi_reg_cfg[`CONFIG_WRITE_OUTRANGE] + 1;
            end
        end
    end
end

// ----------------------
// Config Area Write
// ----------------------
always @(posedge S_AXI_ACLK) begin
    if (!S_AXI_ARESETN) begin
        integer i;
        for (i = 0; i < CONFIG_AREA; i = i + 1) begin
            axi_reg_cfg[i] <= 0;
        end
    end
    else begin
        if (S_AXI_WREADY && S_AXI_WVALID && S_AXI_AWREADY && S_AXI_AWVALID && is_config_area) begin
            axi_reg_cfg[axi_awaddr] <= S_AXI_WDATA;
        end
    end
end

// ----------------------
// Read Address Channel
// ----------------------
always @(posedge S_AXI_ACLK) begin
    if (!S_AXI_ARESETN) begin
        S_AXI_ARREADY <= 1'b0;
        axi_araddr <= 0;
    end
    else begin
        if (~S_AXI_ARREADY && S_AXI_ARVALID) begin
            // 接受读地址
            S_AXI_ARREADY <= 1'b1;
            axi_araddr <= S_AXI_ARADDR;
        end
        else begin
            S_AXI_ARREADY <= 1'b0;
        end
    end
end

// ----------------------
// Read Data Channel
// ----------------------
always @(posedge S_AXI_ACLK) begin
    if (!S_AXI_ARESETN) begin
        S_AXI_RVALID <= 1'b0;
        S_AXI_RDATA <= 0;
    end
    else begin
        if (S_AXI_ARREADY && S_AXI_ARVALID && ~S_AXI_RVALID) begin
            // 读数据就绪
            S_AXI_RVALID <= 1'b1;
            S_AXI_RDATA <= axi_reg_rw[axi_araddr];
        end
        else if (S_AXI_RVALID && S_AXI_RREADY) begin
            // 读数据被接受
            S_AXI_RVALID <= 1'b0;
        end
    end
end

endmodule

axi_interface/wave.vcd
$version Generated by VerilatedVcd $end
$timescale 1ps $end
 $scope module TOP $end
  $var wire 1 Z! S_AXI_ACLK $end
  $var wire 1 [! S_AXI_ARESETN $end
  $var wire 8 \! S_AXI_AWADDR [7:0] $end
  $var wire 1 ]! S_AXI_AWVALID $end
  $var wire 1 ^! S_AXI_AWREADY $end
  $var wire 32 _! S_AXI_WDATA [31:0] $end
  $var wire 1 `! S_AXI_WVALID $end
  $var wire 1 a! S_AXI_WREADY $end
  $var wire 8 b! S_AXI_ARADDR [7:0] $end
  $var wire 1 c! S_AXI_ARVALID $end
  $var wire 1 d! S_AXI_ARREADY $end
  $var wire 32 e! S_AXI_RDATA [31:0] $end
  $var wire 1 f! S_AXI_RVALID $end
  $var wire 1 g! S_AXI_RREADY $end
  $scope module axi_self_test $end
   $var wire 32 h! C_S_AXI_ID_WIDTH [31:0] $end
   $var wire 32 i! C_S_AXI_DATA_WIDTH [31:0] $end
   $var wire 32 j! C_S_AXI_ADDR_WIDTH [31:0] $end
   $var wire 32 k! C_S_AXI_AWUSER_WIDTH [31:0] $end
   $var wire 32 k! C_S_AXI_ARUSER_WIDTH [31:0] $end
   $var wire 32 k! C_S_AXI_WUSER_WIDTH [31:0] $end
   $var wire 32 k! C_S_AXI_RUSER_WIDTH [31:0] $end
   $var wire 32 k! C_S_AXI_BUSER_WIDTH [31:0] $end
   $var wire 32 l! CONFIG_AREA [31:0] $end
   $var wire 32 m! WRITE_AREA [31:0] $end
   $var wire 32 m! READ_AREA [31:0] $end
   $var wire 1 Z! S_AXI_ACLK $end
   $var wire 1 [! S_AXI_ARESETN $end
   $var wire 8 \! S_AXI_AWADDR [7:0] $end
   $var wire 1 ]! S_AXI_AWVALID $end
   $var wire 1 ^! S_AXI_AWREADY $end
   $var wire 32 _! S_AXI_WDATA [31:0] $end
   $var wire 1 `! S_AXI_WVALID $end
   $var wire 1 a! S_AXI_WREADY $end
   $var wire 8 b! S_AXI_ARADDR [7:0] $end
   $var wire 1 c! S_AXI_ARVALID $end
   $var wire 1 d! S_AXI_ARREADY $end
   $var wire 32 e! S_AXI_RDATA [31:0] $end
   $var wire 1 f! S_AXI_RVALID $end
   $var wire 1 g! S_AXI_RREADY $end
   $var wire 32 n! REG_RW_DEPTH [31:0] $end
   $var wire 32 # axi_reg_rw[0] [31:0] $end
   $var wire 32 $ axi_reg_rw[1] [31:0] $end
   $var wire 32 % axi_reg_rw[2] [31:0] $end
   $var wire 32 & axi_reg_rw[3] [31:0] $end
   $var wire 32 ' axi_reg_rw[4] [31:0] $end
   $var wire 32 ( axi_reg_rw[5] [31:0] $end
   $var wire 32 ) axi_reg_rw[6] [31:0] $end
   $var wire 32 * axi_reg_rw[7] [31:0] $end
   $var wire 32 + axi_reg_rw[8] [31:0] $end
   $var wire 32 , axi_reg_rw[9] [31:0] $end
   $var wire 32 - axi_reg_rw[10] [31:0] $end
   $var wire 32 . axi_reg_rw[11] [31:0] $end
   $var wire 32 / axi_reg_rw[12] [31:0] $end
   $var wire 32 0 axi_reg_rw[13] [31:0] $end
   $var wire 32 1 axi_reg_rw[14] [31:0] $end
   $var wire 32 2 axi_reg_rw[15] [31:0] $end
   $var wire 32 3 axi_reg_rw[16] [31:0] $end
   $var wire 32 4 axi_reg_rw[17] [31:0] $end
   $var wire 32 5 axi_reg_rw[18] [31:0] $end
   $var wire 32 6 axi_reg_rw[19] [31:0] $end
   $var wire 32 7 axi_reg_rw[20] [31:0] $end
   $var wire 32 8 axi_reg_rw[21] [31:0] $end
   $var wire 32 9 axi_reg_rw[22] [31:0] $end
   $var wire 32 : axi_reg_rw[23] [31:0] $end
   $var wire 32 ; axi_reg_rw[24] [31:0] $end
   $var wire 32 < axi_reg_rw[25] [31:0] $end
   $var wire 32 = axi_reg_rw[26] [31:0] $end
   $var wire 32 > axi_reg_rw[27] [31:0] $end
   $var wire 32 ? axi_reg_rw[28] [31:0] $end
   $var wire 32 @ axi_reg_rw[29] [31:0] $end
   $var wire 32 A axi_reg_rw[30] [31:0] $end
   $var wire 32 B axi_reg_rw[31] [31:0] $end
   $var wire 32 C axi_reg_rw[32] [31:0] $end
   $var wire 32 D axi_reg_rw[33] [31:0] $end
   $var wire 32 E axi_reg_rw[34] [31:0] $end
   $var wire 32 F axi_reg_rw[35] [31:0] $end
   $var wire 32 G axi_reg_rw[36] [31:0] $end
   $var wire 32 H axi_reg_rw[37] [31:0] $end
   $var wire 32 I axi_reg_rw[38] [31:0] $end
   $var wire 32 J axi_reg_rw[39] [31:0] $end
   $var wire 32 K axi_reg_rw[40] [31:0] $end
   $var wire 32 L axi_reg_rw[41] [31:0] $end
   $var wire 32 M axi_reg_rw[42] [31:0] $end
   $var wire 32 N axi_reg_rw[43] [31:0] $end
   $var wire 32 O axi_reg_rw[44] [31:0] $end
   $var wire 32 P axi_reg_rw[45] [31:0] $end
   $var wire 32 Q axi_reg_rw[46] [31:0] $end
   $var wire 32 R axi_reg_rw[47] [31:0] $end
   $var wire 32 S axi_reg_rw[48] [31:0] $end
   $var wire 32 T axi_reg_rw[49] [31:0] $end
   $var wire 32 U axi_reg_rw[50] [31:0] $end
   $var wire 32 V axi_reg_rw[51] [31:0] $end
   $var wire 32 W axi_reg_rw[52] [31:0] $end
   $var wire 32 X axi_reg_rw[53] [31:0] $end
   $var wire 32 Y axi_reg_rw[54] [31:0] $end
   $var wire 32 Z axi_reg_rw[55] [31:0] $end
   $var wire 32 [ axi_reg_rw[56] [31:0] $end
   $var wire 32 \ axi_reg_rw[57] [31:0] $end
   $var wire 32 ] axi_reg_rw[58] [31:0] $end
   $var wire 32 ^ axi_reg_rw[59] [31:0] $end
   $var wire 32 _ axi_reg_rw[60] [31:0] $end
   $var wire 32 ` axi_reg_rw[61] [31:0] $end
   $var wire 32 a axi_reg_rw[62] [31:0] $end
   $var wire 32 b axi_reg_rw[63] [31:0] $end
   $var wire 32 c axi_reg_rw[64] [31:0] $end
   $var wire 32 d axi_reg_rw[65] [31:0] $end
   $var wire 32 e axi_reg_rw[66] [31:0] $end
   $var wire 32 f axi_reg_rw[67] [31:0] $end
   $var wire 32 g axi_reg_rw[68] [31:0] $end
   $var wire 32 h axi_reg_rw[69] [31:0] $end
   $var wire 32 i axi_reg_rw[70] [31:0] $end
   $var wire 32 j axi_reg_rw[71] [31:0] $end
   $var wire 32 k axi_reg_rw[72] [31:0] $end
   $var wire 32 l axi_reg_rw[73] [31:0] $end
   $var wire 32 m axi_reg_rw[74] [31:0] $end
   $var wire 32 n axi_reg_rw[75] [31:0] $end
   $var wire 32 o axi_reg_rw[76] [31:0] $end
   $var wire 32 p axi_reg_rw[77] [31:0] $end
   $var wire 32 q axi_reg_rw[78] [31:0] $end
   $var wire 32 r axi_reg_rw[79] [31:0] $end
   $var wire 32 s axi_reg_rw[80] [31:0] $end
   $var wire 32 t axi_reg_rw[81] [31:0] $end
   $var wire 32 u axi_reg_rw[82] [31:0] $end
   $var wire 32 v axi_reg_rw[83] [31:0] $end
   $var wire 32 w axi_reg_rw[84] [31:0] $end
   $var wire 32 x axi_reg_rw[85] [31:0] $end
   $var wire 32 y axi_reg_rw[86] [31:0] $end
   $var wire 32 z axi_reg_rw[87] [31:0] $end
   $var wire 32 { axi_reg_rw[88] [31:0] $end
   $var wire 32 | axi_reg_rw[89] [31:0] $end
   $var wire 32 } axi_reg_rw[90] [31:0] $end
   $var wire 32 ~ axi_reg_rw[91] [31:0] $end
   $var wire 32 !! axi_reg_rw[92] [31:0] $end
   $var wire 32 "! axi_reg_rw[93] [31:0] $end
   $var wire 32 #! axi_reg_rw[94] [31:0] $end
   $var wire 32 $! axi_reg_rw[95] [31:0] $end
   $var wire 32 %! axi_reg_rw[96] [31:0] $end
   $var wire 32 &! axi_reg_rw[97] [31:0] $end
   $var wire 32 '! axi_reg_rw[98] [31:0] $end
   $var wire 32 (! axi_reg_rw[99] [31:0] $end
   $var wire 32 )! axi_reg_rw[100] [31:0] $end
   $var wire 32 *! axi_reg_rw[101] [31:0] $end
   $var wire 32 +! axi_reg_rw[102] [31:0] $end
   $var wire 32 ,! axi_reg_rw[103] [31:0] $end
   $var wire 32 -! axi_reg_rw[104] [31:0] $end
   $var wire 32 .! axi_reg_rw[105] [31:0] $end
   $var wire 32 /! axi_reg_rw[106] [31:0] $end
   $var wire 32 0! axi_reg_rw[107] [31:0] $end
   $var wire 32 1! axi_reg_rw[108] [31:0] $end
   $var wire 32 2! axi_reg_rw[109] [31:0] $end
   $var wire 32 3! axi_reg_rw[110] [31:0] $end
   $var wire 32 4! axi_reg_rw[111] [31:0] $end
   $var wire 32 5! axi_reg_rw[112] [31:0] $end
   $var wire 32 6! axi_reg_rw[113] [31:0] $end
   $var wire 32 7! axi_reg_rw[114] [31:0] $end
   $var wire 32 8! axi_reg_rw[115] [31:0] $end
   $var wire 32 9! axi_reg_rw[116] [31:0] $end
   $var wire 32 :! axi_reg_rw[117] [31:0] $end
   $var wire 32 ;! axi_reg_rw[118] [31:0] $end
   $var wire 32 <! axi_reg_rw[119] [31:0] $end
   $var wire 32 =! axi_reg_rw[120] [31:0] $end
   $var wire 32 >! axi_reg_rw[121] [31:0] $end
   $var wire 32 ?! axi_reg_rw[122] [31:0] $end
   $var wire 32 @! axi_reg_rw[123] [31:0] $end
   $var wire 32 A! axi_reg_rw[124] [31:0] $end
   $var wire 32 B! axi_reg_rw[125] [31:0] $end
   $var wire 32 C! axi_reg_rw[126] [31:0] $end
   $var wire 32 D! axi_reg_rw[127] [31:0] $end
   $var wire 32 E! axi_reg_cfg[0] [31:0] $end
   $var wire 32 F! axi_reg_cfg[1] [31:0] $end
   $var wire 32 G! axi_reg_cfg[2] [31:0] $end
   $var wire 32 H! axi_reg_cfg[3] [31:0] $end
   $var wire 32 I! axi_reg_cfg[4] [31:0] $end
   $var wire 32 J! axi_reg_cfg[5] [31:0] $end
   $var wire 32 K! axi_reg_cfg[6] [31:0] $end
   $var wire 32 L! axi_reg_cfg[7] [31:0] $end
   $var wire 32 M! axi_reg_cfg[8] [31:0] $end
   $var wire 32 N! axi_reg_cfg[9] [31:0] $end
   $var wire 32 O! axi_reg_cfg[10] [31:0] $end
   $var wire 32 P! axi_reg_cfg[11] [31:0] $end
   $var wire 32 Q! axi_reg_cfg[12] [31:0] $end
   $var wire 32 R! axi_reg_cfg[13] [31:0] $end
   $var wire 32 S! axi_reg_cfg[14] [31:0] $end
   $var wire 32 T! axi_reg_cfg[15] [31:0] $end
   $var wire 1 U! is_config_area $end
   $var wire 8 V! axi_araddr [7:0] $end
   $var wire 8 W! axi_awaddr [7:0] $end
   $scope module unnamedblk1 $end
    $var wire 32 X! i [31:0] $end
   $upscope $end
   $scope module unnamedblk2 $end
    $var wire 32 Y! i [31:0] $end
   $upscope $end
  $upscope $end
 $upscope $end
$enddefinitions $end


#0
b00000000000000000000000000000000 #
b00000000000000000000000000000000 $
b00000000000000000000000000000000 %
b00000000000000000000000000000000 &
b00000000000000000000000000000000 '
b00000000000000000000000000000000 (
b00000000000000000000000000000000 )
b00000000000000000000000000000000 *
b00000000000000000000000000000000 +
b00000000000000000000000000000000 ,
b00000000000000000000000000000000 -
b00000000000000000000000000000000 .
b00000000000000000000000000000000 /
b00000000000000000000000000000000 0
b00000000000000000000000000000000 1
b00000000000000000000000000000000 2
b00000000000000000000000000000000 3
b00000000000000000000000000000000 4
b00000000000000000000000000000000 5
b00000000000000000000000000000000 6
b00000000000000000000000000000000 7
b00000000000000000000000000000000 8
b00000000000000000000000000000000 9
b00000000000000000000000000000000 :
b00000000000000000000000000000000 ;
b00000000000000000000000000000000 <
b00000000000000000000000000000000 =
b00000000000000000000000000000000 >
b00000000000000000000000000000000 ?
b00000000000000000000000000000000 @
b00000000000000000000000000000000 A
b00000000000000000000000000000000 B
b00000000000000000000000000000000 C
b00000000000000000000000000000000 D
b00000000000000000000000000000000 E
b00000000000000000000000000000000 F
b00000000000000000000000000000000 G
b00000000000000000000000000000000 H
b00000000000000000000000000000000 I
b00000000000000000000000000000000 J
b00000000000000000000000000000000 K
b00000000000000000000000000000000 L
b00000000000000000000000000000000 M
b00000000000000000000000000000000 N
b00000000000000000000000000000000 O
b00000000000000000000000000000000 P
b00000000000000000000000000000000 Q
b00000000000000000000000000000000 R
b00000000000000000000000000000000 S
b00000000000000000000000000000000 T
b00000000000000000000000000000000 U
b00000000000000000000000000000000 V
b00000000000000000000000000000000 W
b00000000000000000000000000000000 X
b00000000000000000000000000000000 Y
b00000000000000000000000000000000 Z
b00000000000000000000000000000000 [
b00000000000000000000000000000000 \
b00000000000000000000000000000000 ]
b00000000000000000000000000000000 ^
b00000000000000000000000000000000 _
b00000000000000000000000000000000 `
b00000000000000000000000000000000 a
b00000000000000000000000000000000 b
b00000000000000000000000000000000 c
b00000000000000000000000000000000 d
b00000000000000000000000000000000 e
b00000000000000000000000000000000 f
b00000000000000000000000000000000 g
b00000000000000000000000000000000 h
b00000000000000000000000000000000 i
b00000000000000000000000000000000 j
b00000000000000000000000000000000 k
b00000000000000000000000000000000 l
b00000000000000000000000000000000 m
b00000000000000000000000000000000 n
b00000000000000000000000000000000 o
b00000000000000000000000000000000 p
b00000000000000000000000000000000 q
b00000000000000000000000000000000 r
b00000000000000000000000000000000 s
b00000000000000000000000000000000 t
b00000000000000000000000000000000 u
b00000000000000000000000000000000 v
b00000000000000000000000000000000 w
b00000000000000000000000000000000 x
b00000000000000000000000000000000 y
b00000000000000000000000000000000 z
b00000000000000000000000000000000 {
b00000000000000000000000000000000 |
b00000000000000000000000000000000 }
b00000000000000000000000000000000 ~
b00000000000000000000000000000000 !!
b00000000000000000000000000000000 "!
b00000000000000000000000000000000 #!
b00000000000000000000000000000000 $!
b00000000000000000000000000000000 %!
b00000000000000000000000000000000 &!
b00000000000000000000000000000000 '!
b00000000000000000000000000000000 (!
b00000000000000000000000000000000 )!
b00000000000000000000000000000000 *!
b00000000000000000000000000000000 +!
b00000000000000000000000000000000 ,!
b00000000000000000000000000000000 -!
b00000000000000000000000000000000 .!
b00000000000000000000000000000000 /!
b00000000000000000000000000000000 0!
b00000000000000000000000000000000 1!
b00000000000000000000000000000000 2!
b00000000000000000000000000000000 3!
b00000000000000000000000000000000 4!
b00000000000000000000000000000000 5!
b00000000000000000000000000000000 6!
b00000000000000000000000000000000 7!
b00000000000000000000000000000000 8!
b00000000000000000000000000000000 9!
b00000000000000000000000000000000 :!
b00000000000000000000000000000000 ;!
b00000000000000000000000000000000 <!
b00000000000000000000000000000000 =!
b00000000000000000000000000000000 >!
b00000000000000000000000000000000 ?!
b00000000000000000000000000000000 @!
b00000000000000000000000000000000 A!
b00000000000000000000000000000000 B!
b00000000000000000000000000000000 C!
b00000000000000000000000000000000 D!
b00000000000000000000000000000000 E!
b00000000000000000000000000000000 F!
b00000000000000000000000000000000 G!
b00000000000000000000000000000000 H!
b00000000000000000000000000000000 I!
b00000000000000000000000000000000 J!
b00000000000000000000000000000000 K!
b00000000000000000000000000000000 L!
b00000000000000000000000000000000 M!
b00000000000000000000000000000000 N!
b00000000000000000000000000000000 O!
b00000000000000000000000000000000 P!
b00000000000000000000000000000000 Q!
b00000000000000000000000000000000 R!
b00000000000000000000000000000000 S!
b00000000000000000000000000000000 T!
0U!
b00000000 V!
b00000000 W!
b00000000000000000000000000000000 X!
b00000000000000000000000000000000 Y!
0Z!
0[!
b00000000 \!
0]!
0^!
b00000000000000000000000000000000 _!
0`!
0a!
b00000000 b!
0c!
0d!
b00000000000000000000000000000000 e!
0f!
0g!
b00000000000000000000000000000001 h!
b00000000000000000000000000100000 i!
b00000000000000000000000000001000 j!
b00000000000000000000000000000000 k!
b00000000000000000000000000010000 l!
b00000000000000000000000001000000 m!
b00000000000000000000000010000000 n!
#1
b00000000000000000000000010000000 X!
b00000000000000000000000000010000 Y!
1Z!
#2
0Z!
#3
1Z!
#4
0Z!
#5
1Z!
#6
0Z!
1[!
1]!
b00000000000000000000000001111111 _!
1`!
#7
1Z!
1^!
1a!
#8
0Z!
#9
b00000000000000000000000001111111 #
1Z!
0^!
0a!
#10
0Z!
#11
1Z!
1^!
1a!
#12
0Z!
#13
1Z!
0^!
0a!
#14
0Z!
#15
1Z!
1^!
1a!
#16
0Z!
#17
1Z!
0^!
0a!
#18
0Z!
#19
1Z!
1^!
1a!
#20
0Z!
#21
1Z!
0^!
0a!
#22
0Z!
#23
1Z!
1^!
1a!
#24
0Z!
#25
1Z!
0^!
0a!
#26
0Z!
#27
1Z!
1^!
1a!
#28
0Z!
#29
1Z!
0^!
0a!
#30
0Z!
#31
1Z!
1^!
1a!
#32
0Z!
#33
1Z!
0^!
0a!
#34
0Z!
#35
1Z!
1^!
1a!
#36
0Z!
#37
1Z!
0^!
0a!
#38
0Z!
#39
1Z!
1^!
1a!
#40
0Z!
#41
1Z!
0^!
0a!
#42
0Z!
#43
1Z!
1^!
1a!
#44
0Z!
#45
1Z!
0^!
0a!
#46
0Z!
#47
1Z!
1^!
1a!
#48
0Z!
#49
1Z!
0^!
0a!
#50
0Z!
#51
1Z!
1^!
1a!
#52
0Z!
#53
1Z!
0^!
0a!
#54
0Z!
#55
1Z!
1^!
1a!
#56
0Z!
#57
1Z!
0^!
0a!
#58
0Z!
#59
1Z!
1^!
1a!
#60
0Z!
#61
1Z!
0^!
0a!
#62
0Z!
#63
1Z!
1^!
1a!
#64
0Z!
#65
1Z!
0^!
0a!
#66
0Z!
#67
1Z!
1^!
1a!
#68
0Z!
#69
1Z!
0^!
0a!
#70
0Z!
#71
1Z!
1^!
1a!
#72
0Z!
#73
1Z!
0^!
0a!
#74
0Z!
#75
1Z!
1^!
1a!
#76
0Z!
#77
1Z!
0^!
0a!
#78
0Z!
#79
1Z!
1^!
1a!
#80
0Z!
#81
1Z!
0^!
0a!
#82
0Z!
#83
1Z!
1^!
1a!
#84
0Z!
#85
1Z!
0^!
0a!
#86
0Z!
#87
1Z!
1^!
1a!
#88
0Z!
#89
1Z!
0^!
0a!
#90
0Z!
#91
1Z!
1^!
1a!
#92
0Z!
#93
1Z!
0^!
0a!
#94
0Z!
#95
1Z!
1^!
1a!
#96
0Z!
#97
1Z!
0^!
0a!
#98
0Z!
#99
1Z!
1^!
1a!
#100
0Z!
#101
1Z!
0^!
0a!
#102
0Z!
#103
1Z!
1^!
1a!
#104
0Z!
#105
1Z!
0^!
0a!
#106
0Z!
#107
1Z!
1^!
1a!
#108
0Z!
#109
1Z!
0^!
0a!
#110
0Z!
#111
1Z!
1^!
1a!
#112
0Z!
#113
1Z!
0^!
0a!
#114
0Z!
#115
1Z!
1^!
1a!
#116
0Z!
#117
1Z!
0^!
0a!
#118
0Z!
#119
1Z!
1^!
1a!
#120
0Z!
#121
1Z!
0^!
0a!
#122
0Z!
#123
1Z!
1^!
1a!
#124
0Z!
#125
1Z!
0^!
0a!
#126
0Z!
#127
1Z!
1^!
1a!
#128
0Z!
#129
1Z!
0^!
0a!
#130
0Z!
#131
1Z!
1^!
1a!
#132
0Z!
#133
1Z!
0^!
0a!
#134
0Z!
#135
1Z!
1^!
1a!
#136
0Z!
#137
1Z!
0^!
0a!
#138
0Z!
#139
1Z!
1^!
1a!
#140
0Z!
#141
1Z!
0^!
0a!
#142
0Z!
#143
1Z!
1^!
1a!
#144
0Z!
#145
1Z!
0^!
0a!
#146
0Z!
#147
1Z!
1^!
1a!
#148
0Z!
#149
1Z!
0^!
0a!
#150
0Z!
#151
1Z!
1^!
1a!
#152
0Z!
#153
1Z!
0^!
0a!
#154
0Z!
#155
1Z!
1^!
1a!
#156
0Z!
#157
1Z!
0^!
0a!
#158
0Z!
#159
1Z!
1^!
1a!
#160
0Z!
#161
1Z!
0^!
0a!
#162
0Z!
#163
1Z!
1^!
1a!
#164
0Z!
#165
1Z!
0^!
0a!
#166
0Z!
#167
1Z!
1^!
1a!
#168
0Z!
#169
1Z!
0^!
0a!
#170
0Z!
#171
1Z!
1^!
1a!
#172
0Z!
#173
1Z!
0^!
0a!
#174
0Z!
#175
1Z!
1^!
1a!
#176
0Z!
#177
1Z!
0^!
0a!
#178
0Z!
#179
1Z!
1^!
1a!
#180
0Z!
#181
1Z!
0^!
0a!
#182
0Z!
#183
1Z!
1^!
1a!
#184
0Z!
#185
1Z!
0^!
0a!
#186
0Z!
#187
1Z!
1^!
1a!
#188
0Z!
#189
1Z!
0^!
0a!
#190
0Z!
#191
1Z!
1^!
1a!
#192
0Z!
#193
1Z!
0^!
0a!
#194
0Z!
#195
1Z!
1^!
1a!
#196
0Z!
#197
1Z!
0^!
0a!
#198
0Z!
#199
1Z!
1^!
1a!
#200
0Z!
#201
1Z!
0^!
0a!
#202
0Z!
#203
1Z!
1^!
1a!
#204
0Z!
#205
1Z!
0^!
0a!
#206
0Z!
#207
1Z!
1^!
1a!
#208
0Z!
#209
1Z!
0^!
0a!
#210
0Z!
#211
1Z!
1^!
1a!
#212
0Z!
#213
1Z!
0^!
0a!
#214
0Z!
#215
1Z!
1^!
1a!
#216
0Z!
#217
1Z!
0^!
0a!
#218
0Z!
#219
1Z!
1^!
1a!
#220
0Z!
#221
1Z!
0^!
0a!
#222
0Z!
#223
1Z!
1^!
1a!
#224
0Z!
#225
1Z!
0^!
0a!
#226
0Z!
#227
1Z!
1^!
1a!
#228
0Z!
#229
1Z!
0^!
0a!
#230
0Z!
#231
1Z!
1^!
1a!
#232
0Z!
#233
1Z!
0^!
0a!
#234
0Z!
#235
1Z!
1^!
1a!
#236
0Z!
#237
1Z!
0^!
0a!
#238
0Z!
#239
1Z!
1^!
1a!
#240
0Z!
#241
1Z!
0^!
0a!
#242
0Z!
#243
1Z!
1^!
1a!
#244
0Z!
#245
1Z!
0^!
0a!
#246
0Z!
#247
1Z!
1^!
1a!
#248
0Z!
#249
1Z!
0^!
0a!
#250
0Z!
#251
1Z!
1^!
1a!
#252
0Z!
#253
1Z!
0^!
0a!
#254
0Z!
#255
1Z!
1^!
1a!
#256
0Z!
#257
1Z!
0^!
0a!
#258
0Z!
#259
1Z!
1^!
1a!
#260
0Z!
#261
1Z!
0^!
0a!
#262
0Z!
#263
1Z!
1^!
1a!
#264
0Z!
#265
1Z!
0^!
0a!
#266
0Z!
#267
1Z!
1^!
1a!
#268
0Z!
#269
1Z!
0^!
0a!
#270
0Z!
#271
1Z!
1^!
1a!
#272
0Z!
#273
1Z!
0^!
0a!
#274
0Z!
#275
1Z!
1^!
1a!
#276
0Z!
#277
1Z!
0^!
0a!
#278
0Z!
#279
1Z!
1^!
1a!
#280
0Z!
#281
1Z!
0^!
0a!
#282
0Z!
#283
1Z!
1^!
1a!
#284
0Z!
#285
1Z!
0^!
0a!
#286
0Z!
#287
1Z!
1^!
1a!
#288
0Z!
#289
1Z!
0^!
0a!
#290
0Z!
#291
1Z!
1^!
1a!
#292
0Z!
#293
1Z!
0^!
0a!
#294
0Z!
#295
1Z!
1^!
1a!
#296
0Z!
#297
1Z!
0^!
0a!
#298
0Z!
#299
1Z!
1^!
1a!
#300
0Z!
#301
1Z!
0^!
0a!
#302
0Z!
#303
1Z!
1^!
1a!
#304
0Z!
#305
1Z!
0^!
0a!
#306
0Z!
#307
1Z!
1^!
1a!
#308
0Z!
#309
1Z!
0^!
0a!
#310
0Z!
#311
1Z!
1^!
1a!
#312
0Z!
#313
1Z!
0^!
0a!
#314
0Z!
#315
1Z!
1^!
1a!
#316
0Z!
#317
1Z!
0^!
0a!
#318
0Z!
#319
1Z!
1^!
1a!
#320
0Z!
#321
1Z!
0^!
0a!
#322
0Z!
#323
1Z!
1^!
1a!
#324
0Z!
#325
1Z!
0^!
0a!
#326
0Z!
#327
1Z!
1^!
1a!
#328
0Z!
#329
1Z!
0^!
0a!
#330
0Z!
#331
1Z!
1^!
1a!
#332
0Z!
#333
1Z!
0^!
0a!
#334
0Z!
#335
1Z!
1^!
1a!
#336
0Z!
#337
1Z!
0^!
0a!
#338
0Z!
#339
1Z!
1^!
1a!
#340
0Z!
#341
1Z!
0^!
0a!
#342
0Z!
#343
1Z!
1^!
1a!
#344
0Z!
#345
1Z!
0^!
0a!
#346
0Z!
#347
1Z!
1^!
1a!
#348
0Z!
#349
1Z!
0^!
0a!
#350
0Z!
#351
1Z!
1^!
1a!
#352
0Z!
#353
1Z!
0^!
0a!
#354
0Z!
#355
1Z!
1^!
1a!
#356
0Z!
#357
1Z!
0^!
0a!
#358
0Z!
#359
1Z!
1^!
1a!
#360
0Z!
#361
1Z!
0^!
0a!
#362
0Z!
#363
1Z!
1^!
1a!
#364
0Z!
#365
1Z!
0^!
0a!
#366
0Z!
